{
	"Changes": [
		{
			"LogName": "ESC - Fishing Difficulty 5% Harder",
			"Action": "EditData",
			"Target": "Data/Fish",
			"Fields": {
			    "EastScarp_Golden_Trout": {1: "{{Round: {{Query: (80 + (80 * 0.05)) }} }}"},
				"EastScarp_Kokanee_Salmon": {1: "{{Round: {{Query: (75 + (75 * 0.05)) }} }}"},
				"EastScarp_King_Carp": {1: "{{Round: {{Query: (90 + (90 * 0.05)) }} }}"},
				"EastScarp_Cerulean_Nudibranch": {1: "{{Round: {{Query: (70 + (70 * 0.05)) }} }}"},
				"EastScarp_Ornate_Nudibranch": {1: "{{Round: {{Query: (80 + (80 * 0.05)) }} }}"},
				"EastScarp_Sea_Bunny_Nudibranch": {1: "{{Round: {{Query: (80 + (80 * 0.05)) }} }}"},
				"EastScarp_Sunset_Nudibranch": {1: "{{Round: {{Query: (80 + (80 * 0.05)) }} }}"},
				"EastScarp_Red_Herring": {1: "{{Round: {{Query: (65 + (65 * 0.05)) }} }}"},
				"EastScarp_Fairy_Betta": {1: "{{Round: {{Query: (75 + (75 * 0.05)) }} }}"},
				"EastScarp_Obsidian_Maw": {1: "{{Round: {{Query: (80 + (80 * 0.05)) }} }}"},
				"EastScarp_Slime_Barbel": {1: "{{Round: {{Query: (80 + (80 * 0.05)) }} }}"},
					},
				"When": {"Fishing Difficulty": "5% Harder"},
		},
		{
			"LogName": "ESC - Fishing Difficulty 10% Harder",
			"Action": "EditData",
			"Target": "Data/Fish",
			"Fields": {
			    "EastScarp_Golden_Trout": {1: "{{Round: {{Query: (80 + (80 * 0.10)) }} }}"},
				"EastScarp_Kokanee_Salmon": {1: "{{Round: {{Query: (75 + (75 * 0.10)) }} }}"},
				"EastScarp_King_Carp": {1: "{{Round: {{Query: (90 + (90 * 0.10)) }} }}"},
				"EastScarp_Cerulean_Nudibranch": {1: "{{Round: {{Query: (70 + (70 * 0.10)) }} }}"},
				"EastScarp_Ornate_Nudibranch": {1: "{{Round: {{Query: (80 + (80 * 0.10)) }} }}"},
				"EastScarp_Sea_Bunny_Nudibranch": {1: "{{Round: {{Query: (80 + (80 * 0.10)) }} }}"},
				"EastScarp_Sunset_Nudibranch": {1: "{{Round: {{Query: (80 + (80 * 0.10)) }} }}"},
				"EastScarp_Red_Herring": {1: "{{Round: {{Query: (65 + (65 * 0.10)) }} }}"},
				"EastScarp_Fairy_Betta": {1: "{{Round: {{Query: (75 + (75 * 0.10)) }} }}"},
				"EastScarp_Obsidian_Maw": {1: "{{Round: {{Query: (80 + (80 * 0.10)) }} }}"},
				"EastScarp_Slime_Barbel": {1: "{{Round: {{Query: (80 + (80 * 0.10)) }} }}"},
					},
				"When": {"Fishing Difficulty": "10% Harder"},
		},
		{
			"LogName": "ESC - Fishing Difficulty 15% Harder",
			"Action": "EditData",
			"Target": "Data/Fish",
			"Fields": {
			    "EastScarp_Golden_Trout": {1: "{{Round: {{Query: (80 + (80 * 0.15)) }} }}"},
				"EastScarp_Kokanee_Salmon": {1: "{{Round: {{Query: (75 + (75 * 0.15)) }} }}"},
				"EastScarp_King_Carp": {1: "{{Round: {{Query: (90 + (90 * 0.15)) }} }}"},
				"EastScarp_Cerulean_Nudibranch": {1: "{{Round: {{Query: (70 + (70 * 0.15)) }} }}"},
				"EastScarp_Ornate_Nudibranch": {1: "{{Round: {{Query: (80 + (80 * 0.15)) }} }}"},
				"EastScarp_Sea_Bunny_Nudibranch": {1: "{{Round: {{Query: (80 + (80 * 0.15)) }} }}"},
				"EastScarp_Sunset_Nudibranch": {1: "{{Round: {{Query: (80 + (80 * 0.15)) }} }}"},
				"EastScarp_Red_Herring": {1: "{{Round: {{Query: (65 + (65 * 0.15)) }} }}"},
				"EastScarp_Fairy_Betta": {1: "{{Round: {{Query: (75 + (75 * 0.15)) }} }}"},
				"EastScarp_Obsidian_Maw": {1: "{{Round: {{Query: (80 + (80 * 0.15)) }} }}"},
				"EastScarp_Slime_Barbel": {1: "{{Round: {{Query: (80 + (80 * 0.15)) }} }}"},
					},
				"When": {"Fishing Difficulty": "15% Harder"},
		},
		{
			"LogName": "ESC - Fishing Difficulty 20% Harder",
			"Action": "EditData",
			"Target": "Data/Fish",
			"Fields": {
			    "EastScarp_Golden_Trout": {1: "{{Round: {{Query: (80 + (80 * 0.20)) }} }}"},
				"EastScarp_Kokanee_Salmon": {1: "{{Round: {{Query: (75 + (75 * 0.20)) }} }}"},
				"EastScarp_King_Carp": {1: "{{Round: {{Query: (90 + (90 * 0.20)) }} }}"},
				"EastScarp_Cerulean_Nudibranch": {1: "{{Round: {{Query: (70 + (70 * 0.20)) }} }}"},
				"EastScarp_Ornate_Nudibranch": {1: "{{Round: {{Query: (80 + (80 * 0.20)) }} }}"},
				"EastScarp_Sea_Bunny_Nudibranch": {1: "{{Round: {{Query: (80 + (80 * 0.20)) }} }}"},
				"EastScarp_Sunset_Nudibranch": {1: "{{Round: {{Query: (80 + (80 * 0.20)) }} }}"},
				"EastScarp_Red_Herring": {1: "{{Round: {{Query: (65 + (65 * 0.20)) }} }}"},
				"EastScarp_Fairy_Betta": {1: "{{Round: {{Query: (75 + (75 * 0.20)) }} }}"},
				"EastScarp_Obsidian_Maw": {1: "{{Round: {{Query: (80 + (80 * 0.20)) }} }}"},
				"EastScarp_Slime_Barbel": {1: "{{Round: {{Query: (80 + (80 * 0.20)) }} }}"},
					},
				"When": {"Fishing Difficulty": "20% Harder"},
		},
		{
			"LogName": "ESC - Fishing Difficulty 25% Harder",
			"Action": "EditData",
			"Target": "Data/Fish",
			"Fields": {
			    "EastScarp_Golden_Trout": {1: "{{Round: {{Query: (80 + (80 * 0.25)) }} }}"},
				"EastScarp_Kokanee_Salmon": {1: "{{Round: {{Query: (75 + (75 * 0.25)) }} }}"},
				"EastScarp_King_Carp": {1: "{{Round: {{Query: (90 + (90 * 0.25)) }} }}"},
				"EastScarp_Cerulean_Nudibranch": {1: "{{Round: {{Query: (70 + (70 * 0.25)) }} }}"},
				"EastScarp_Ornate_Nudibranch": {1: "{{Round: {{Query: (80 + (80 * 0.25)) }} }}"},
				"EastScarp_Sea_Bunny_Nudibranch": {1: "{{Round: {{Query: (80 + (80 * 0.25)) }} }}"},
				"EastScarp_Sunset_Nudibranch": {1: "{{Round: {{Query: (80 + (80 * 0.25)) }} }}"},
				"EastScarp_Red_Herring": {1: "{{Round: {{Query: (65 + (65 * 0.25)) }} }}"},
				"EastScarp_Fairy_Betta": {1: "{{Round: {{Query: (75 + (75 * 0.25)) }} }}"},
				"EastScarp_Obsidian_Maw": {1: "{{Round: {{Query: (80 + (80 * 0.25)) }} }}"},
				"EastScarp_Slime_Barbel": {1: "{{Round: {{Query: (80 + (80 * 0.25)) }} }}"},
					},
				"When": {"Fishing Difficulty": "25% Harder"},
		},
		{
			"LogName": "ESC - Fishing Difficulty 30% Harder",
			"Action": "EditData",
			"Target": "Data/Fish",
			"Fields": {
			    "EastScarp_Golden_Trout": {1: "{{Round: {{Query: (80 + (80 * 0.30)) }} }}"},
				"EastScarp_Kokanee_Salmon": {1: "{{Round: {{Query: (75 + (75 * 0.30)) }} }}"},
				"EastScarp_King_Carp": {1: "{{Round: {{Query: (90 + (90 * 0.30)) }} }}"},
				"EastScarp_Cerulean_Nudibranch": {1: "{{Round: {{Query: (70 + (70 * 0.30)) }} }}"},
				"EastScarp_Ornate_Nudibranch": {1: "{{Round: {{Query: (80 + (80 * 0.30)) }} }}"},
				"EastScarp_Sea_Bunny_Nudibranch": {1: "{{Round: {{Query: (80 + (80 * 0.30)) }} }}"},
				"EastScarp_Sunset_Nudibranch": {1: "{{Round: {{Query: (80 + (80 * 0.30)) }} }}"},
				"EastScarp_Red_Herring": {1: "{{Round: {{Query: (65 + (65 * 0.30)) }} }}"},
				"EastScarp_Fairy_Betta": {1: "{{Round: {{Query: (75 + (75 * 0.30)) }} }}"},
				"EastScarp_Obsidian_Maw": {1: "{{Round: {{Query: (80 + (80 * 0.30)) }} }}"},
				"EastScarp_Slime_Barbel": {1: "{{Round: {{Query: (80 + (80 * 0.30)) }} }}"},
					},
				"When": {"Fishing Difficulty": "30% Harder"},
		},
		{
			"LogName": "ESC - Fishing Difficulty 35% Harder",
			"Action": "EditData",
			"Target": "Data/Fish",
			"Fields": {
			    "EastScarp_Golden_Trout": {1: "{{Round: {{Query: (80 + (80 * 0.35)) }} }}"},
				"EastScarp_Kokanee_Salmon": {1: "{{Round: {{Query: (75 + (75 * 0.35)) }} }}"},
				"EastScarp_King_Carp": {1: "{{Round: {{Query: (90 + (90 * 0.35)) }} }}"},
				"EastScarp_Cerulean_Nudibranch": {1: "{{Round: {{Query: (70 + (70 * 0.35)) }} }}"},
				"EastScarp_Ornate_Nudibranch": {1: "{{Round: {{Query: (80 + (80 * 0.35)) }} }}"},
				"EastScarp_Sea_Bunny_Nudibranch": {1: "{{Round: {{Query: (80 + (80 * 0.35)) }} }}"},
				"EastScarp_Sunset_Nudibranch": {1: "{{Round: {{Query: (80 + (80 * 0.35)) }} }}"},
				"EastScarp_Red_Herring": {1: "{{Round: {{Query: (65 + (65 * 0.35)) }} }}"},
				"EastScarp_Fairy_Betta": {1: "{{Round: {{Query: (75 + (75 * 0.35)) }} }}"},
				"EastScarp_Obsidian_Maw": {1: "{{Round: {{Query: (80 + (80 * 0.35)) }} }}"},
				"EastScarp_Slime_Barbel": {1: "{{Round: {{Query: (80 + (80 * 0.35)) }} }}"},
					},
				"When": {"Fishing Difficulty": "35% Harder"},
		},
		{
			"LogName": "ESC - Fishing Difficulty 40% Harder",
			"Action": "EditData",
			"Target": "Data/Fish",
			"Fields": {
			    "EastScarp_Golden_Trout": {1: "{{Round: {{Query: (80 + (80 * 0.40)) }} }}"},
				"EastScarp_Kokanee_Salmon": {1: "{{Round: {{Query: (75 + (75 * 0.40)) }} }}"},
				"EastScarp_King_Carp": {1: "{{Round: {{Query: (90 + (90 * 0.40)) }} }}"},
				"EastScarp_Cerulean_Nudibranch": {1: "{{Round: {{Query: (70 + (70 * 0.40)) }} }}"},
				"EastScarp_Ornate_Nudibranch": {1: "{{Round: {{Query: (80 + (80 * 0.40)) }} }}"},
				"EastScarp_Sea_Bunny_Nudibranch": {1: "{{Round: {{Query: (80 + (80 * 0.40)) }} }}"},
				"EastScarp_Sunset_Nudibranch": {1: "{{Round: {{Query: (80 + (80 * 0.40)) }} }}"},
				"EastScarp_Red_Herring": {1: "{{Round: {{Query: (65 + (65 * 0.40)) }} }}"},
				"EastScarp_Fairy_Betta": {1: "{{Round: {{Query: (75 + (75 * 0.40)) }} }}"},
				"EastScarp_Obsidian_Maw": {1: "{{Round: {{Query: (80 + (80 * 0.40)) }} }}"},
				"EastScarp_Slime_Barbel": {1: "{{Round: {{Query: (80 + (80 * 0.40)) }} }}"},
					},
				"When": {"Fishing Difficulty": "40% Harder"},
		},
		{
			"LogName": "ESC - Fishing Difficulty 45% Harder",
			"Action": "EditData",
			"Target": "Data/Fish",
			"Fields": {
			    "EastScarp_Golden_Trout": {1: "{{Round: {{Query: (80 + (80 * 0.45)) }} }}"},
				"EastScarp_Kokanee_Salmon": {1: "{{Round: {{Query: (75 + (75 * 0.45)) }} }}"},
				"EastScarp_King_Carp": {1: "{{Round: {{Query: (90 + (90 * 0.45)) }} }}"},
				"EastScarp_Cerulean_Nudibranch": {1: "{{Round: {{Query: (70 + (70 * 0.45)) }} }}"},
				"EastScarp_Ornate_Nudibranch": {1: "{{Round: {{Query: (80 + (80 * 0.45)) }} }}"},
				"EastScarp_Sea_Bunny_Nudibranch": {1: "{{Round: {{Query: (80 + (80 * 0.45)) }} }}"},
				"EastScarp_Sunset_Nudibranch": {1: "{{Round: {{Query: (80 + (80 * 0.45)) }} }}"},
				"EastScarp_Red_Herring": {1: "{{Round: {{Query: (65 + (65 * 0.45)) }} }}"},
				"EastScarp_Fairy_Betta": {1: "{{Round: {{Query: (75 + (75 * 0.45)) }} }}"},
				"EastScarp_Obsidian_Maw": {1: "{{Round: {{Query: (80 + (80 * 0.45)) }} }}"},
				"EastScarp_Slime_Barbel": {1: "{{Round: {{Query: (80 + (80 * 0.45)) }} }}"},
					},
				"When": {"Fishing Difficulty": "45% Harder"},
		},
		{
			"LogName": "ESC - Fishing Difficulty 50% Harder",
			"Action": "EditData",
			"Target": "Data/Fish",
			"Fields": {
			    "EastScarp_Golden_Trout": {1: "{{Round: {{Query: (80 + (80 * 0.50)) }} }}"},
				"EastScarp_Kokanee_Salmon": {1: "{{Round: {{Query: (75 + (75 * 0.50)) }} }}"},
				"EastScarp_King_Carp": {1: "{{Round: {{Query: (90 + (90 * 0.50)) }} }}"},
				"EastScarp_Cerulean_Nudibranch": {1: "{{Round: {{Query: (70 + (70 * 0.50)) }} }}"},
				"EastScarp_Ornate_Nudibranch": {1: "{{Round: {{Query: (80 + (80 * 0.50)) }} }}"},
				"EastScarp_Sea_Bunny_Nudibranch": {1: "{{Round: {{Query: (80 + (80 * 0.50)) }} }}"},
				"EastScarp_Sunset_Nudibranch": {1: "{{Round: {{Query: (80 + (80 * 0.50)) }} }}"},
				"EastScarp_Red_Herring": {1: "{{Round: {{Query: (65 + (65 * 0.50)) }} }}"},
				"EastScarp_Fairy_Betta": {1: "{{Round: {{Query: (75 + (75 * 0.50)) }} }}"},
				"EastScarp_Obsidian_Maw": {1: "{{Round: {{Query: (80 + (80 * 0.50)) }} }}"},
				"EastScarp_Slime_Barbel": {1: "{{Round: {{Query: (80 + (80 * 0.50)) }} }}"},
					},
				"When": {"Fishing Difficulty": "50% Harder"},
		},
		{
			"LogName": "ESC - Fishing Difficulty 55% Harder",
			"Action": "EditData",
			"Target": "Data/Fish",
			"Fields": {
			    "EastScarp_Golden_Trout": {1: "{{Round: {{Query: (80 + (80 * 0.55)) }} }}"},
				"EastScarp_Kokanee_Salmon": {1: "{{Round: {{Query: (75 + (75 * 0.55)) }} }}"},
				"EastScarp_King_Carp": {1: "{{Round: {{Query: (90 + (90 * 0.55)) }} }}"},
				"EastScarp_Cerulean_Nudibranch": {1: "{{Round: {{Query: (70 + (70 * 0.55)) }} }}"},
				"EastScarp_Ornate_Nudibranch": {1: "{{Round: {{Query: (80 + (80 * 0.55)) }} }}"},
				"EastScarp_Sea_Bunny_Nudibranch": {1: "{{Round: {{Query: (80 + (80 * 0.55)) }} }}"},
				"EastScarp_Sunset_Nudibranch": {1: "{{Round: {{Query: (80 + (80 * 0.55)) }} }}"},
				"EastScarp_Red_Herring": {1: "{{Round: {{Query: (65 + (65 * 0.55)) }} }}"},
				"EastScarp_Fairy_Betta": {1: "{{Round: {{Query: (75 + (75 * 0.55)) }} }}"},
				"EastScarp_Obsidian_Maw": {1: "{{Round: {{Query: (80 + (80 * 0.55)) }} }}"},
				"EastScarp_Slime_Barbel": {1: "{{Round: {{Query: (80 + (80 * 0.55)) }} }}"},
					},
				"When": {"Fishing Difficulty": "55% Harder"},
		},
		{
			"LogName": "ESC - Fishing Difficulty 60% Harder",
			"Action": "EditData",
			"Target": "Data/Fish",
			"Fields": {
			    "EastScarp_Golden_Trout": {1: "{{Round: {{Query: (80 + (80 * 0.60)) }} }}"},
				"EastScarp_Kokanee_Salmon": {1: "{{Round: {{Query: (75 + (75 * 0.60)) }} }}"},
				"EastScarp_King_Carp": {1: "{{Round: {{Query: (90 + (90 * 0.60)) }} }}"},
				"EastScarp_Cerulean_Nudibranch": {1: "{{Round: {{Query: (70 + (70 * 0.60)) }} }}"},
				"EastScarp_Ornate_Nudibranch": {1: "{{Round: {{Query: (80 + (80 * 0.60)) }} }}"},
				"EastScarp_Sea_Bunny_Nudibranch": {1: "{{Round: {{Query: (80 + (80 * 0.60)) }} }}"},
				"EastScarp_Sunset_Nudibranch": {1: "{{Round: {{Query: (80 + (80 * 0.60)) }} }}"},
				"EastScarp_Red_Herring": {1: "{{Round: {{Query: (65 + (65 * 0.60)) }} }}"},
				"EastScarp_Fairy_Betta": {1: "{{Round: {{Query: (75 + (75 * 0.60)) }} }}"},
				"EastScarp_Obsidian_Maw": {1: "{{Round: {{Query: (80 + (80 * 0.60)) }} }}"},
				"EastScarp_Slime_Barbel": {1: "{{Round: {{Query: (80 + (80 * 0.60)) }} }}"},
					},
				"When": {"Fishing Difficulty": "60% Harder"},
		},
		{
			"LogName": "ESC - Fishing Difficulty 65% Harder",
			"Action": "EditData",
			"Target": "Data/Fish",
			"Fields": {
			    "EastScarp_Golden_Trout": {1: "{{Round: {{Query: (80 + (80 * 0.65)) }} }}"},
				"EastScarp_Kokanee_Salmon": {1: "{{Round: {{Query: (75 + (75 * 0.65)) }} }}"},
				"EastScarp_King_Carp": {1: "{{Round: {{Query: (90 + (90 * 0.65)) }} }}"},
				"EastScarp_Cerulean_Nudibranch": {1: "{{Round: {{Query: (70 + (70 * 0.65)) }} }}"},
				"EastScarp_Ornate_Nudibranch": {1: "{{Round: {{Query: (80 + (80 * 0.65)) }} }}"},
				"EastScarp_Sea_Bunny_Nudibranch": {1: "{{Round: {{Query: (80 + (80 * 0.65)) }} }}"},
				"EastScarp_Sunset_Nudibranch": {1: "{{Round: {{Query: (80 + (80 * 0.65)) }} }}"},
				"EastScarp_Red_Herring": {1: "{{Round: {{Query: (65 + (65 * 0.65)) }} }}"},
				"EastScarp_Fairy_Betta": {1: "{{Round: {{Query: (75 + (75 * 0.65)) }} }}"},
				"EastScarp_Obsidian_Maw": {1: "{{Round: {{Query: (80 + (80 * 0.65)) }} }}"},
				"EastScarp_Slime_Barbel": {1: "{{Round: {{Query: (80 + (80 * 0.65)) }} }}"},
					},
				"When": {"Fishing Difficulty": "65% Harder"},
		},
		{
			"LogName": "ESC - Fishing Difficulty 70% Harder",
			"Action": "EditData",
			"Target": "Data/Fish",
			"Fields": {
			    "EastScarp_Golden_Trout": {1: "{{Round: {{Query: (80 + (80 * 0.70)) }} }}"},
				"EastScarp_Kokanee_Salmon": {1: "{{Round: {{Query: (75 + (75 * 0.70)) }} }}"},
				"EastScarp_King_Carp": {1: "{{Round: {{Query: (90 + (90 * 0.70)) }} }}"},
				"EastScarp_Cerulean_Nudibranch": {1: "{{Round: {{Query: (70 + (70 * 0.70)) }} }}"},
				"EastScarp_Ornate_Nudibranch": {1: "{{Round: {{Query: (80 + (80 * 0.70)) }} }}"},
				"EastScarp_Sea_Bunny_Nudibranch": {1: "{{Round: {{Query: (80 + (80 * 0.70)) }} }}"},
				"EastScarp_Sunset_Nudibranch": {1: "{{Round: {{Query: (80 + (80 * 0.70)) }} }}"},
				"EastScarp_Red_Herring": {1: "{{Round: {{Query: (65 + (65 * 0.70)) }} }}"},
				"EastScarp_Fairy_Betta": {1: "{{Round: {{Query: (75 + (75 * 0.70)) }} }}"},
				"EastScarp_Obsidian_Maw": {1: "{{Round: {{Query: (80 + (80 * 0.70)) }} }}"},
				"EastScarp_Slime_Barbel": {1: "{{Round: {{Query: (80 + (80 * 0.70)) }} }}"},
					},
				"When": {"Fishing Difficulty": "70% Harder"},
		},
		{
			"LogName": "ESC - Fishing Difficulty 75% Harder",
			"Action": "EditData",
			"Target": "Data/Fish",
			"Fields": {
			    "EastScarp_Golden_Trout": {1: "{{Round: {{Query: (80 + (80 * 0.75)) }} }}"},
				"EastScarp_Kokanee_Salmon": {1: "{{Round: {{Query: (75 + (75 * 0.75)) }} }}"},
				"EastScarp_King_Carp": {1: "{{Round: {{Query: (90 + (90 * 0.75)) }} }}"},
				"EastScarp_Cerulean_Nudibranch": {1: "{{Round: {{Query: (70 + (70 * 0.75)) }} }}"},
				"EastScarp_Ornate_Nudibranch": {1: "{{Round: {{Query: (80 + (80 * 0.75)) }} }}"},
				"EastScarp_Sea_Bunny_Nudibranch": {1: "{{Round: {{Query: (80 + (80 * 0.75)) }} }}"},
				"EastScarp_Sunset_Nudibranch": {1: "{{Round: {{Query: (80 + (80 * 0.75)) }} }}"},
				"EastScarp_Red_Herring": {1: "{{Round: {{Query: (65 + (65 * 0.75)) }} }}"},
				"EastScarp_Fairy_Betta": {1: "{{Round: {{Query: (75 + (75 * 0.75)) }} }}"},
				"EastScarp_Obsidian_Maw": {1: "{{Round: {{Query: (80 + (80 * 0.75)) }} }}"},
				"EastScarp_Slime_Barbel": {1: "{{Round: {{Query: (80 + (80 * 0.75)) }} }}"},
					},
				"When": {"Fishing Difficulty": "75% Harder"},
		},
		{
			"LogName": "ESC - Fishing Difficulty 80% Harder",
			"Action": "EditData",
			"Target": "Data/Fish",
			"Fields": {
			    "EastScarp_Golden_Trout": {1: "{{Round: {{Query: (80 + (80 * 0.80)) }} }}"},
				"EastScarp_Kokanee_Salmon": {1: "{{Round: {{Query: (75 + (75 * 0.80)) }} }}"},
				"EastScarp_King_Carp": {1: "{{Round: {{Query: (90 + (90 * 0.80)) }} }}"},
				"EastScarp_Cerulean_Nudibranch": {1: "{{Round: {{Query: (70 + (70 * 0.80)) }} }}"},
				"EastScarp_Ornate_Nudibranch": {1: "{{Round: {{Query: (80 + (80 * 0.80)) }} }}"},
				"EastScarp_Sea_Bunny_Nudibranch": {1: "{{Round: {{Query: (80 + (80 * 0.80)) }} }}"},
				"EastScarp_Sunset_Nudibranch": {1: "{{Round: {{Query: (80 + (80 * 0.80)) }} }}"},
				"EastScarp_Red_Herring": {1: "{{Round: {{Query: (65 + (65 * 0.80)) }} }}"},
				"EastScarp_Fairy_Betta": {1: "{{Round: {{Query: (75 + (75 * 0.80)) }} }}"},
				"EastScarp_Obsidian_Maw": {1: "{{Round: {{Query: (80 + (80 * 0.80)) }} }}"},
				"EastScarp_Slime_Barbel": {1: "{{Round: {{Query: (80 + (80 * 0.80)) }} }}"},
					},
				"When": {"Fishing Difficulty": "80% Harder"},
		},
		{
			"LogName": "ESC - Fishing Difficulty 85% Harder",
			"Action": "EditData",
			"Target": "Data/Fish",
			"Fields": {
			    "EastScarp_Golden_Trout": {1: "{{Round: {{Query: (80 + (80 * 0.85)) }} }}"},
				"EastScarp_Kokanee_Salmon": {1: "{{Round: {{Query: (75 + (75 * 0.85)) }} }}"},
				"EastScarp_King_Carp": {1: "{{Round: {{Query: (90 + (90 * 0.85)) }} }}"},
				"EastScarp_Cerulean_Nudibranch": {1: "{{Round: {{Query: (70 + (70 * 0.85)) }} }}"},
				"EastScarp_Ornate_Nudibranch": {1: "{{Round: {{Query: (80 + (80 * 0.85)) }} }}"},
				"EastScarp_Sea_Bunny_Nudibranch": {1: "{{Round: {{Query: (80 + (80 * 0.85)) }} }}"},
				"EastScarp_Sunset_Nudibranch": {1: "{{Round: {{Query: (80 + (80 * 0.85)) }} }}"},
				"EastScarp_Red_Herring": {1: "{{Round: {{Query: (65 + (65 * 0.85)) }} }}"},
				"EastScarp_Fairy_Betta": {1: "{{Round: {{Query: (75 + (75 * 0.85)) }} }}"},
				"EastScarp_Obsidian_Maw": {1: "{{Round: {{Query: (80 + (80 * 0.85)) }} }}"},
				"EastScarp_Slime_Barbel": {1: "{{Round: {{Query: (80 + (80 * 0.85)) }} }}"},
					},
				"When": {"Fishing Difficulty": "85% Harder"},
		},
		{
			"LogName": "ESC - Fishing Difficulty 90% Harder",
			"Action": "EditData",
			"Target": "Data/Fish",
			"Fields": {
			    "EastScarp_Golden_Trout": {1: "{{Round: {{Query: (80 + (80 * 0.90)) }} }}"},
				"EastScarp_Kokanee_Salmon": {1: "{{Round: {{Query: (75 + (75 * 0.90)) }} }}"},
				"EastScarp_King_Carp": {1: "{{Round: {{Query: (90 + (90 * 0.90)) }} }}"},
				"EastScarp_Cerulean_Nudibranch": {1: "{{Round: {{Query: (70 + (70 * 0.90)) }} }}"},
				"EastScarp_Ornate_Nudibranch": {1: "{{Round: {{Query: (80 + (80 * 0.90)) }} }}"},
				"EastScarp_Sea_Bunny_Nudibranch": {1: "{{Round: {{Query: (80 + (80 * 0.90)) }} }}"},
				"EastScarp_Sunset_Nudibranch": {1: "{{Round: {{Query: (80 + (80 * 0.90)) }} }}"},
				"EastScarp_Red_Herring": {1: "{{Round: {{Query: (65 + (65 * 0.90)) }} }}"},
				"EastScarp_Fairy_Betta": {1: "{{Round: {{Query: (75 + (75 * 0.90)) }} }}"},
				"EastScarp_Obsidian_Maw": {1: "{{Round: {{Query: (80 + (80 * 0.90)) }} }}"},
				"EastScarp_Slime_Barbel": {1: "{{Round: {{Query: (80 + (80 * 0.90)) }} }}"},
					},
				"When": {"Fishing Difficulty": "90% Harder"},
		},
		{
			"LogName": "ESC - Fishing Difficulty 95% Harder",
			"Action": "EditData",
			"Target": "Data/Fish",
			"Fields": {
			    "EastScarp_Golden_Trout": {1: "{{Round: {{Query: (80 + (80 * 0.95)) }} }}"},
				"EastScarp_Kokanee_Salmon": {1: "{{Round: {{Query: (75 + (75 * 0.95)) }} }}"},
				"EastScarp_King_Carp": {1: "{{Round: {{Query: (90 + (90 * 0.95)) }} }}"},
				"EastScarp_Cerulean_Nudibranch": {1: "{{Round: {{Query: (70 + (70 * 0.95)) }} }}"},
				"EastScarp_Ornate_Nudibranch": {1: "{{Round: {{Query: (80 + (80 * 0.95)) }} }}"},
				"EastScarp_Sea_Bunny_Nudibranch": {1: "{{Round: {{Query: (80 + (80 * 0.95)) }} }}"},
				"EastScarp_Sunset_Nudibranch": {1: "{{Round: {{Query: (80 + (80 * 0.95)) }} }}"},
				"EastScarp_Red_Herring": {1: "{{Round: {{Query: (65 + (65 * 0.95)) }} }}"},
				"EastScarp_Fairy_Betta": {1: "{{Round: {{Query: (75 + (75 * 0.95)) }} }}"},
				"EastScarp_Obsidian_Maw": {1: "{{Round: {{Query: (80 + (80 * 0.95)) }} }}"},
				"EastScarp_Slime_Barbel": {1: "{{Round: {{Query: (80 + (80 * 0.95)) }} }}"},
					},
				"When": {"Fishing Difficulty": "95% Harder"},
		},
		{
			"LogName": "ESC - Fishing Difficulty 100% Harder",
			"Action": "EditData",
			"Target": "Data/Fish",
			"Fields": {
			    "EastScarp_Golden_Trout": {1: "{{Round: {{Query: (80 + (80 * 1)) }} }}"},
				"EastScarp_Kokanee_Salmon": {1: "{{Round: {{Query: (75 + (75 * 1)) }} }}"},
				"EastScarp_King_Carp": {1: "{{Round: {{Query: (90 + (90 * 1)) }} }}"},
				"EastScarp_Cerulean_Nudibranch": {1: "{{Round: {{Query: (70 + (70 * 1)) }} }}"},
				"EastScarp_Ornate_Nudibranch": {1: "{{Round: {{Query: (80 + (80 * 1)) }} }}"},
				"EastScarp_Sea_Bunny_Nudibranch": {1: "{{Round: {{Query: (80 + (80 * 1)) }} }}"},
				"EastScarp_Sunset_Nudibranch": {1: "{{Round: {{Query: (80 + (80 * 1)) }} }}"},
				"EastScarp_Red_Herring": {1: "{{Round: {{Query: (65 + (65 * 1)) }} }}"},
				"EastScarp_Fairy_Betta": {1: "{{Round: {{Query: (75 + (75 * 1)) }} }}"},
				"EastScarp_Obsidian_Maw": {1: "{{Round: {{Query: (80 + (80 * 1)) }} }}"},
				"EastScarp_Slime_Barbel": {1: "{{Round: {{Query: (80 + (80 * 1)) }} }}"},
					},
				"When": {"Fishing Difficulty": "100% Harder"},
		},
		{
			"LogName": "ESC - Fishing Difficulty NIGHTMARE",
			"Action": "EditData",
			"Target": "Data/Fish",
			"Fields": {
			    "EastScarp_Golden_Trout": {1: "{{Round: {{Query: (80 + (80 * 8)) }} }}"},
				"EastScarp_Kokanee_Salmon": {1: "{{Round: {{Query: (75 + (75 * 8)) }} }}"},
				"EastScarp_King_Carp": {1: "{{Round: {{Query: (90 + (90 * 8)) }} }}"},
				"EastScarp_Cerulean_Nudibranch": {1: "{{Round: {{Query: (70 + (70 * 8)) }} }}"},
				"EastScarp_Ornate_Nudibranch": {1: "{{Round: {{Query: (80 + (80 * 8)) }} }}"},
				"EastScarp_Sea_Bunny_Nudibranch": {1: "{{Round: {{Query: (80 + (80 * 8)) }} }}"},
				"EastScarp_Sunset_Nudibranch": {1: "{{Round: {{Query: (80 + (80 * 8)) }} }}"},
				"EastScarp_Red_Herring": {1: "{{Round: {{Query: (65 + (65 * 8)) }} }}"},
				"EastScarp_Fairy_Betta": {1: "{{Round: {{Query: (75 + (75 * 8)) }} }}"},
				"EastScarp_Obsidian_Maw": {1: "{{Round: {{Query: (80 + (80 * 8)) }} }}"},
				"EastScarp_Slime_Barbel": {1: "{{Round: {{Query: (80 + (80 * 8)) }} }}"},
					},
				"When": {"Fishing Difficulty": "NIGHTMARE"},
		},
	]
}