{
	"Changes": [
		{
			"LogName": "MNF - All Seasons Forest",
			"Action": "EditData",
			"Target": "Data/Locations",
			"TargetField": [ "Forest", "Fish" ],
			"Fields": {
				"MNF.MoreNewFish_lionhead": {"Season": null, "Condition": null},
				"MNF.MoreNewFish_comet": {"Season": null, "Condition": null},
				"MNF.MoreNewFish_telescope": {"Season": null, "Condition": null},
				"MNF.MoreNewFish_celestial_eye": {"Season": null, "Condition": null},
				"MNF.MoreNewFish_freshwater_butterflyfish": {"Season": null, "Condition": null},
				"MNF.MoreNewFish_clown_loach": {"Season": null, "Condition": null},
				"MNF.MoreNewFish_elephantfish": {"Season": null, "Condition": null},
				"MNF.MoreNewFish_pangasius": {"Season": null, "Condition": null},
				"MNF.MoreNewFish_siamese_algae_eater": {"Season": null, "Condition": null},
				"MNF.MoreNewFish_common_pleco": {"Season": null, "Condition": null},
				"MNF.MoreNewFish_redtail_shark": {"Season": null, "Condition": null},
				"MNF.MoreNewFish_tench": {"Season": null, "Condition": null},
				"MNF.MoreNewFish_snowball_pleco": {"Season": null, "Condition": null},
				"MNF.MoreNewFish_sauger": {"Season": null, "Condition": null},
				"MNF.MoreNewFish_ide": {"Season": null, "Condition": null},
				"MNF.MoreNewFish_trahira": {"Season": null, "Condition": null},
				"MNF.MoreNewFish_pacu": {"Season": null, "Condition": null},
				"MNF.MoreNewFish_tucunare": {"Season": null, "Condition": null},
				"MNF.MoreNewFish_freshwater_pufferfish": {"Season": null, "Condition": null},
				"MNF.MoreNewFish_arctic_char": {"Season": null, "Condition": null},
				      },
			    "When": {"All Seasons": true},
	    },
		{
			"LogName": "MNF - All Seasons Beach",
			"Action": "EditData",
			"Target": "Data/Locations",
			"TargetField": [ "Beach", "Fish" ],
			"Fields": {
				"MNF.MoreNewFish_ladyfish": {"Season": null, "Condition": null},
				"MNF.MoreNewFish_sea_snake": {"Season": null, "Condition": null},
				"MNF.MoreNewFish_anchoviella": {"Season": null, "Condition": null},
				"MNF.MoreNewFish_barracuda": {"Season": null, "Condition": null},
				"MNF.MoreNewFish_spiny_dogfish": {"Season": null, "Condition": null},
				"MNF.MoreNewFish_mimic_octopus": {"Season": null, "Condition": null},
				"MNF.MoreNewFish_zebra_eel": {"Season": null, "Condition": null},
				"MNF.MoreNewFish_small_manta_ray": {"Season": null, "Condition": null},
				"MNF.MoreNewFish_ribbon_eel": {"Season": null, "Condition": null},
				"MNF.MoreNewFish_robalo": {"Season": null, "Condition": null},
				"MNF.MoreNewFish_haddock": {"Season": null, "Condition": null},
				"MNF.MoreNewFish_small_swordfish": {"Season": null, "Condition": null},
				"MNF.MoreNewFish_blue_ringed_octopus": {"Season": null, "Condition": null},
				"MNF.MoreNewFish_ghost_eel": {"Season": null, "Condition": null},
				"MNF.MoreNewFish_longfin_icedevil": {"Season": null, "Condition": null},
				"MNF.MoreNewFish_small_goblin_shark": {"Season": null, "Condition": null},
				"MNF.MoreNewFish_stubby_squid": {"Season": null, "Condition": null},
				"MNF.MoreNewFish_dumbo_octopus": {"Season": null, "Condition": null},
				"MNF.MoreNewFish_hagfish": {"Season": null, "Condition": null},
				"MNF.MoreNewFish_conger": {"Season": null, "Condition": null},
				"MNF.MoreNewFish_king_crab": {"Season": null, "Condition": null},
				      },
			    "When": {"All Seasons": true},
	    },
		{
			"LogName": "MNF - All Seasons Woods",
			"Action": "EditData",
			"Target": "Data/Locations",
			"TargetField": [ "Woods", "Fish" ],
			"Fields": {
				"MNF.MoreNewFish_kohaku_koi": {"Season": null, "Condition": null},
				"MNF.MoreNewFish_yamabuki_koi": {"Season": null, "Condition": null},
				"MNF.MoreNewFish_sanke_koi": {"Season": null, "Condition": null},
				"MNF.MoreNewFish_ki_utsuri_koi": {"Season": null, "Condition": null},
				"MNF.MoreNewFish_tancho_koi": {"Season": null, "Condition": null},
				"MNF.MoreNewFish_ghost_koi": {"Season": null, "Condition": null},
				"MNF.MoreNewFish_hi_utsuri_koi": {"Season": null, "Condition": null},
				"MNF.MoreNewFish_shiro_utsuri_koi": {"Season": null, "Condition": null},
				      },
			    "When": {"All Seasons": true},
	    },
		{
			"LogName": "MNF - All Seasons Town",
			"Action": "EditData",
			"Target": "Data/Locations",
			"TargetField": [ "Town", "Fish" ],
			"Fields": {
				"MNF.MoreNewFish_green_terror": {"Season": null, "Condition": null},
				"MNF.MoreNewFish_siamese_algae_eater": {"Season": null, "Condition": null},
				"MNF.MoreNewFish_common_pleco": {"Season": null, "Condition": null},
				"MNF.MoreNewFish_freshwater_pufferfish": {"Season": null, "Condition": null},
				"MNF.MoreNewFish_snowball_pleco": {"Season": null, "Condition": null},
				"MNF.MoreNewFish_trahira": {"Season": null, "Condition": null},
				"MNF.MoreNewFish_pacu": {"Season": null, "Condition": null},
				      },
			    "When": {"All Seasons": true},
	    },
		{
			"LogName": "MNF - All Seasons Mountain",
			"Action": "EditData",
			"Target": "Data/Locations",
			"TargetField": [ "Mountain", "Fish" ],
			"Fields": {
				"MNF.MoreNewFish_clown_loach": {"Season": null, "Condition": null},
				"MNF.MoreNewFish_elephantfish": {"Season": null, "Condition": null},
				"MNF.MoreNewFish_zebra_tilapia": {"Season": null, "Condition": null},
				"MNF.MoreNewFish_pangasius": {"Season": null, "Condition": null},
				"MNF.MoreNewFish_siamese_algae_eater": {"Season": null, "Condition": null},
				"MNF.MoreNewFish_common_pleco": {"Season": null, "Condition": null},
				"MNF.MoreNewFish_freshwater_pufferfish": {"Season": null, "Condition": null},
				"MNF.MoreNewFish_trahira": {"Season": null, "Condition": null},
				"MNF.MoreNewFish_pacu": {"Season": null, "Condition": null},
				"MNF.MoreNewFish_redtail_shark": {"Season": null, "Condition": null},
				"MNF.MoreNewFish_clown_knifefish": {"Season": null, "Condition": null},
				"MNF.MoreNewFish_tench": {"Season": null, "Condition": null},
				"MNF.MoreNewFish_sauger": {"Season": null, "Condition": null},
				"MNF.MoreNewFish_ide": {"Season": null, "Condition": null},
				"MNF.MoreNewFish_snowball_pleco": {"Season": null, "Condition": null},
				      },
			    "When": {"All Seasons": true},
	    },
	]
}