{
	"Changes": [
		{
			"LogName": "Legendary Fish Spawn Rates Common Crimsonfish",
			"Action": "EditData",
			"Target": "Data/Locations",
			"TargetField": [ "Beach", "Fish" ],
			"Fields": { 
				"(O)159": {"Chance": 0.2},
					  },
			    "When": {"Legendary Fish Spawn Rates": "Common (20%)"},
	    },
		{
			"LogName": "Legendary Fish Spawn Rates More Common Crimsonfish",
			"Action": "EditData",
			"Target": "Data/Locations",
			"TargetField": [ "Beach", "Fish" ],
			"Fields": { 
				"(O)159": {"Chance": 0.3},
					  },
			    "When": {"Legendary Fish Spawn Rates": "More Common (30%)"},
	    },
		{
			"LogName": "Legendary Fish Spawn Rates Very Common Crimsonfish",
			"Action": "EditData",
			"Target": "Data/Locations",
			"TargetField": [ "Beach", "Fish" ],
			"Fields": { 
				"(O)159": {"Chance": 0.5},
					  },
			    "When": {"Legendary Fish Spawn Rates": "Very Common (50%)"},
	    },
		{
			"LogName": "Legendary Fish Spawn Rates Rare Crimsonfish",
			"Action": "EditData",
			"Target": "Data/Locations",
			"TargetField": [ "Beach", "Fish" ],
			"Fields": { 
				"(O)159": {"Chance": 0.13},
					  },
			    "When": {"Legendary Fish Spawn Rates": "Rare (7-14%)"},
	    },
		{
			"LogName": "Legendary Fish Spawn Rates Very Rare Crimsonfish",
			"Action": "EditData",
			"Target": "Data/Locations",
			"TargetField": [ "Beach", "Fish" ],
			"Fields": { 
				"(O)159": {"Chance": 0.05},
					  },
			    "When": {"Legendary Fish Spawn Rates": "Very Rare (5%)"},
	    },
		{
			"LogName": "Legendary Fish Spawn Rates Impossible Crimsonfish",
			"Action": "EditData",
			"Target": "Data/Locations",
			"TargetField": [ "Beach", "Fish" ],
			"Fields": { 
				"(O)159": {"Chance": 0.01},
					  },
			    "When": {"Legendary Fish Spawn Rates": "Near Impossible (1%)"},
	    },
		{
			"LogName": "Legendary Fish Spawn Rates Common Angler",
			"Action": "EditData",
			"Target": "Data/Locations",
			"TargetField": [ "Town", "Fish" ],
			"Fields": { 
				"(O)160": {"Chance": 0.2},
					  },
			    "When": {"Legendary Fish Spawn Rates": "Common (20%)"},
	    },
		{
			"LogName": "Legendary Fish Spawn Rates More Common Angler",
			"Action": "EditData",
			"Target": "Data/Locations",
			"TargetField": [ "Town", "Fish" ],
			"Fields": { 
				"(O)160": {"Chance": 0.3},
					  },
			    "When": {"Legendary Fish Spawn Rates": "More Common (30%)"},
	    },
		{
			"LogName": "Legendary Fish Spawn Rates Very Common Angler",
			"Action": "EditData",
			"Target": "Data/Locations",
			"TargetField": [ "Town", "Fish" ],
			"Fields": { 
				"(O)160": {"Chance": 0.5},
					  },
			    "When": {"Legendary Fish Spawn Rates": "Very Common (50%)"},
	    },
		{
			"LogName": "Legendary Fish Spawn Rates Rare Angler",
			"Action": "EditData",
			"Target": "Data/Locations",
			"TargetField": [ "Town", "Fish" ],
			"Fields": { 
				"(O)160": {"Chance": 0.14},
					  },
			    "When": {"Legendary Fish Spawn Rates": "Rare (7-14%)"},
	    },
		{
			"LogName": "Legendary Fish Spawn Rates Very Rare Angler",
			"Action": "EditData",
			"Target": "Data/Locations",
			"TargetField": [ "Town", "Fish" ],
			"Fields": { 
				"(O)160": {"Chance": 0.05},
					  },
			    "When": {"Legendary Fish Spawn Rates": "Very Rare (5%)"},
	    },
		{
			"LogName": "Legendary Fish Spawn Rates Near Impossible Angler",
			"Action": "EditData",
			"Target": "Data/Locations",
			"TargetField": [ "Town", "Fish" ],
			"Fields": { 
				"(O)160": {"Chance": 0.01},
					  },
			    "When": {"Legendary Fish Spawn Rates": "Near Impossible (1%)"},
	    },
		{
			"LogName": "Legendary Fish Spawn Rates Common Legend",
			"Action": "EditData",
			"Target": "Data/Locations",
			"TargetField": [ "Mountain", "Fish" ],
			"Fields": { 
				"(O)163": {"Chance": 0.2},
					  },
			    "When": {"Legendary Fish Spawn Rates": "Common (20%)"},
	    },
		{
			"LogName": "Legendary Fish Spawn Rates More Common Legend",
			"Action": "EditData",
			"Target": "Data/Locations",
			"TargetField": [ "Mountain", "Fish" ],
			"Fields": { 
				"(O)163": {"Chance": 0.3},
					  },
			    "When": {"Legendary Fish Spawn Rates": "More Common (30%)"},
	    },
		{
			"LogName": "Legendary Fish Spawn Rates Very Common Legend",
			"Action": "EditData",
			"Target": "Data/Locations",
			"TargetField": [ "Mountain", "Fish" ],
			"Fields": { 
				"(O)163": {"Chance": 0.5},
					  },
			    "When": {"Legendary Fish Spawn Rates": "Very Common (50%)"},
	    },
		{
			"LogName": "Legendary Fish Spawn Rates Rare Legend",
			"Action": "EditData",
			"Target": "Data/Locations",
			"TargetField": [ "Mountain", "Fish" ],
			"Fields": { 
				"(O)163": {"Chance": 0.07},
					  },
			    "When": {"Legendary Fish Spawn Rates": "Rare (7-14%)"},
	    },
		{
			"LogName": "Legendary Fish Spawn Rates Very Rare Legend",
			"Action": "EditData",
			"Target": "Data/Locations",
			"TargetField": [ "Mountain", "Fish" ],
			"Fields": { 
				"(O)163": {"Chance": 0.05},
					  },
			    "When": {"Legendary Fish Spawn Rates": "Very Rare (5%)"},
	    },
		{
			"LogName": "Legendary Fish Spawn Rates Near Impossible Legend",
			"Action": "EditData",
			"Target": "Data/Locations",
			"TargetField": [ "Mountain", "Fish" ],
			"Fields": { 
				"(O)163": {"Chance": 0.01},
					  },
			    "When": {"Legendary Fish Spawn Rates": "Near Impossible (1%)"},
	    },
		{
			"LogName": "Legendary Fish Spawn Rates Common Mutant Carp",
			"Action": "EditData",
			"Target": "Data/Locations",
			"TargetField": [ "Sewer", "Fish" ],
			"Fields": { 
				"(O)682": {"Chance": 0.2},
					  },
			    "When": {"Legendary Fish Spawn Rates": "Common (20%)"},
	    },
		{
			"LogName": "Legendary Fish Spawn Rates More Common Mutant Carp",
			"Action": "EditData",
			"Target": "Data/Locations",
			"TargetField": [ "Sewer", "Fish" ],
			"Fields": { 
				"(O)682": {"Chance": 0.3},
					  },
			    "When": {"Legendary Fish Spawn Rates": "More Common (30%)"},
	    },
		{
			"LogName": "Legendary Fish Spawn Rates Very Common Mutant Carp",
			"Action": "EditData",
			"Target": "Data/Locations",
			"TargetField": [ "Sewer", "Fish" ],
			"Fields": { 
				"(O)682": {"Chance": 0.5},
					  },
			    "When": {"Legendary Fish Spawn Rates": "Very Common (50%)"},
	    },
		{
			"LogName": "Legendary Fish Spawn Rates Rare Mutant Carp",
			"Action": "EditData",
			"Target": "Data/Locations",
			"TargetField": [ "Sewer", "Fish" ],
			"Fields": { 
				"(O)682": {"Chance": 0.07},
					  },
			    "When": {"Legendary Fish Spawn Rates": "Rare (7-14%)"},
	    },
		{
			"LogName": "Legendary Fish Spawn Rates Very Rare Mutant Carp",
			"Action": "EditData",
			"Target": "Data/Locations",
			"TargetField": [ "Sewer", "Fish" ],
			"Fields": { 
				"(O)682": {"Chance": 0.05},
					  },
			    "When": {"Legendary Fish Spawn Rates": "Very Rare (5%)"},
	    },
		{
			"LogName": "Legendary Fish Spawn Rates Near Impossible Mutant Carp",
			"Action": "EditData",
			"Target": "Data/Locations",
			"TargetField": [ "Sewer", "Fish" ],
			"Fields": { 
				"(O)682": {"Chance": 0.01},
					  },
			    "When": {"Legendary Fish Spawn Rates": "Near Impossible (1%)"},
	    },
		{
			"LogName": "Legendary Fish Spawn Rates Common Glacierfish",
			"Action": "EditData",
			"Target": "Data/Locations",
			"TargetField": [ "Forest", "Fish" ],
			"Fields": { 
				"(O)775": {"Chance": 0.2},
					  },
			    "When": {"Legendary Fish Spawn Rates": "Common (20%)"},
	    },
		{
			"LogName": "Legendary Fish Spawn Rates More Common Glacierfish",
			"Action": "EditData",
			"Target": "Data/Locations",
			"TargetField": [ "Forest", "Fish" ],
			"Fields": { 
				"(O)775": {"Chance": 0.3},
					  },
			    "When": {"Legendary Fish Spawn Rates": "More Common (30%)"},
	    },
		{
			"LogName": "Legendary Fish Spawn Rates Very Common Glacierfish",
			"Action": "EditData",
			"Target": "Data/Locations",
			"TargetField": [ "Forest", "Fish" ],
			"Fields": { 
				"(O)775": {"Chance": 0.5},
					  },
			    "When": {"Legendary Fish Spawn Rates": "Very Common (50%)"},
	    },
		{
			"LogName": "Legendary Fish Spawn Rates Rare Glacierfish",
			"Action": "EditData",
			"Target": "Data/Locations",
			"TargetField": [ "Forest", "Fish" ],
			"Fields": { 
				"(O)775": {"Chance": 0.1},
					  },
			    "When": {"Legendary Fish Spawn Rates": "Rare (7-14%)"},
	    },
		{
			"LogName": "Legendary Fish Spawn Rates Very Rare Glacierfish",
			"Action": "EditData",
			"Target": "Data/Locations",
			"TargetField": [ "Forest", "Fish" ],
			"Fields": { 
				"(O)775": {"Chance": 0.05},
					  },
			    "When": {"Legendary Fish Spawn Rates": "Very Rare (5%)"},
	    },
		{
			"LogName": "Legendary Fish Spawn Rates Near Impossible Glacierfish",
			"Action": "EditData",
			"Target": "Data/Locations",
			"TargetField": [ "Forest", "Fish" ],
			"Fields": {
				"(O)775": {"Chance": 0.01},
					  },
			    "When": {"Legendary Fish Spawn Rates": "Near Impossible (1%)"},
	    },
		{
			"LogName": "Legendary Fish Spawn Rates Farm Standard Common",
			"Action": "EditData",
			"Target": "Data/Locations",
			"TargetField": [ "Farm_Standard", "Fish" ],
			"Fields": { 
				"(O)159": {"Chance": 0.2},
				"(O)160": {"Chance": 0.2},
				"(O)163": {"Chance": 0.2},
				"(O)682": {"Chance": 0.2},
				"(O)775": {"Chance": 0.2},
					  },
			    "When": {"Legendary Fish On Farm": true, "Legendary Fish Spawn Rates": "Common (20%)"},
	    },
		{
			"LogName": "Legendary Fish Spawn Rates Farm Standard More Common",
			"Action": "EditData",
			"Target": "Data/Locations",
			"TargetField": [ "Farm_Standard", "Fish" ],
			"Fields": { 
				"(O)159": {"Chance": 0.3},
				"(O)160": {"Chance": 0.3},
				"(O)163": {"Chance": 0.3},
				"(O)682": {"Chance": 0.3},
				"(O)775": {"Chance": 0.3},
					  },
			    "When": {"Legendary Fish On Farm": true, "Legendary Fish Spawn Rates": "More Common (30%)"},
	    },
		{
			"LogName": "Legendary Fish Spawn Rates Farm Standard Very Common",
			"Action": "EditData",
			"Target": "Data/Locations",
			"TargetField": [ "Farm_Standard", "Fish" ],
			"Fields": { 
				"(O)159": {"Chance": 0.5},
				"(O)160": {"Chance": 0.5},
				"(O)163": {"Chance": 0.5},
				"(O)682": {"Chance": 0.5},
				"(O)775": {"Chance": 0.5},
					  },
			    "When": {"Legendary Fish On Farm": true, "Legendary Fish Spawn Rates": "Very Common (50%)"},
	    },
		{
			"LogName": "Legendary Fish Spawn Rates Farm Standard Rare",
			"Action": "EditData",
			"Target": "Data/Locations",
			"TargetField": [ "Farm_Standard", "Fish" ],
			"Fields": { 
				"(O)159": {"Chance": 0.13},
				"(O)160": {"Chance": 0.14},
				"(O)163": {"Chance": 0.07},
				"(O)682": {"Chance": 0.07},
				"(O)775": {"Chance": 0.10},
					  },
			    "When": {"Legendary Fish On Farm": true, "Legendary Fish Spawn Rates": "Rare (7-14%)"},
	    },
		{
			"LogName": "Legendary Fish Spawn Rates Farm Standard Very Rare",
			"Action": "EditData",
			"Target": "Data/Locations",
			"TargetField": [ "Farm_Standard", "Fish" ],
			"Fields": { 
				"(O)159": {"Chance": 0.05},
				"(O)160": {"Chance": 0.05},
				"(O)163": {"Chance": 0.05},
				"(O)682": {"Chance": 0.05},
				"(O)775": {"Chance": 0.05},
					  },
			    "When": {"Legendary Fish On Farm": true, "Legendary Fish Spawn Rates": "Very Rare (5%)"},
	    },
		{
			"LogName": "Legendary Fish Spawn Rates Farm Standard Near Impossible",
			"Action": "EditData",
			"Target": "Data/Locations",
			"TargetField": [ "Farm_Standard", "Fish" ],
			"Fields": { 
				"(O)159": {"Chance": 0.01},
				"(O)160": {"Chance": 0.01},
				"(O)163": {"Chance": 0.01},
				"(O)682": {"Chance": 0.01},
				"(O)775": {"Chance": 0.01},
					  },
			    "When": {"Legendary Fish On Farm": true, "Legendary Fish Spawn Rates": "Near Impossible (1%)"},
	    },
		{
			"LogName": "Legendary Fish Spawn Rates Farm Beach Common",
			"Action": "EditData",
			"Target": "Data/Locations",
			"TargetField": [ "Farm_Beach", "Fish" ],
			"Fields": { 
				"(O)159": {"Chance": 0.2},
				"(O)160": {"Chance": 0.2},
				"(O)163": {"Chance": 0.2},
				"(O)682": {"Chance": 0.2},
				"(O)775": {"Chance": 0.2},
					  },
			    "When": {"Legendary Fish On Farm": true, "Legendary Fish Spawn Rates": "Common (20%)"},
	    },
		{
			"LogName": "Legendary Fish Spawn Rates Farm Beach More Common",
			"Action": "EditData",
			"Target": "Data/Locations",
			"TargetField": [ "Farm_Beach", "Fish" ],
			"Fields": { 
				"(O)159": {"Chance": 0.3},
				"(O)160": {"Chance": 0.3},
				"(O)163": {"Chance": 0.3},
				"(O)682": {"Chance": 0.3},
				"(O)775": {"Chance": 0.3},
					  },
			    "When": {"Legendary Fish On Farm": true, "Legendary Fish Spawn Rates": "More Common (30%)"},
	    },
		{
			"LogName": "Legendary Fish Spawn Rates Farm Beach Very Common",
			"Action": "EditData",
			"Target": "Data/Locations",
			"TargetField": [ "Farm_Beach", "Fish" ],
			"Fields": { 
				"(O)159": {"Chance": 0.5},
				"(O)160": {"Chance": 0.5},
				"(O)163": {"Chance": 0.5},
				"(O)682": {"Chance": 0.5},
				"(O)775": {"Chance": 0.5},
					  },
			    "When": {"Legendary Fish On Farm": true, "Legendary Fish Spawn Rates": "Very Common (50%)"},
	    },
		{
			"LogName": "Legendary Fish Spawn Rates Farm Beach Rare",
			"Action": "EditData",
			"Target": "Data/Locations",
			"TargetField": [ "Farm_Beach", "Fish" ],
			"Fields": { 
				"(O)159": {"Chance": 0.13},
				"(O)160": {"Chance": 0.14},
				"(O)163": {"Chance": 0.07},
				"(O)682": {"Chance": 0.07},
				"(O)775": {"Chance": 0.10},
					  },
			    "When": {"Legendary Fish On Farm": true, "Legendary Fish Spawn Rates": "Rare (7-14%)"},
	    },
		{
			"LogName": "Legendary Fish Spawn Rates Farm Beach Very Rare",
			"Action": "EditData",
			"Target": "Data/Locations",
			"TargetField": [ "Farm_Beach", "Fish" ],
			"Fields": { 
				"(O)159": {"Chance": 0.05},
				"(O)160": {"Chance": 0.05},
				"(O)163": {"Chance": 0.05},
				"(O)682": {"Chance": 0.05},
				"(O)775": {"Chance": 0.05},
					  },
			    "When": {"Legendary Fish On Farm": true, "Legendary Fish Spawn Rates": "Very Rare (5%)"},
	    },
		{
			"LogName": "Legendary Fish Spawn Rates Farm Beach Near Impossible",
			"Action": "EditData",
			"Target": "Data/Locations",
			"TargetField": [ "Farm_Beach", "Fish" ],
			"Fields": { 
				"(O)159": {"Chance": 0.01},
				"(O)160": {"Chance": 0.01},
				"(O)163": {"Chance": 0.01},
				"(O)682": {"Chance": 0.01},
				"(O)775": {"Chance": 0.01},
					  },
			    "When": {"Legendary Fish On Farm": true, "Legendary Fish Spawn Rates": "Near Impossible (1%)"},
	    },
		{
			"LogName": "Legendary Fish Spawn Rates Farm Forest Common",
			"Action": "EditData",
			"Target": "Data/Locations",
			"TargetField": [ "Farm_Forest", "Fish" ],
			"Fields": { 
				"(O)159": {"Chance": 0.2},
				"(O)160": {"Chance": 0.2},
				"(O)163": {"Chance": 0.2},
				"(O)682": {"Chance": 0.2},
				"(O)775": {"Chance": 0.2},
					  },
			    "When": {"Legendary Fish On Farm": true, "Legendary Fish Spawn Rates": "Common (20%)"},
	    },
		{
			"LogName": "Legendary Fish Spawn Rates Farm Forest More Common",
			"Action": "EditData",
			"Target": "Data/Locations",
			"TargetField": [ "Farm_Forest", "Fish" ],
			"Fields": { 
				"(O)159": {"Chance": 0.3},
				"(O)160": {"Chance": 0.3},
				"(O)163": {"Chance": 0.3},
				"(O)682": {"Chance": 0.3},
				"(O)775": {"Chance": 0.3},
					  },
			    "When": {"Legendary Fish On Farm": true, "Legendary Fish Spawn Rates": "More Common (30%)"},
	    },
		{
			"LogName": "Legendary Fish Spawn Rates Farm Forest Very Common",
			"Action": "EditData",
			"Target": "Data/Locations",
			"TargetField": [ "Farm_Forest", "Fish" ],
			"Fields": { 
				"(O)159": {"Chance": 0.5},
				"(O)160": {"Chance": 0.5},
				"(O)163": {"Chance": 0.5},
				"(O)682": {"Chance": 0.5},
				"(O)775": {"Chance": 0.5},
					  },
			    "When": {"Legendary Fish On Farm": true, "Legendary Fish Spawn Rates": "Very Common (50%)"},
	    },
		{
			"LogName": "Legendary Fish Spawn Rates Farm Forest Rare",
			"Action": "EditData",
			"Target": "Data/Locations",
			"TargetField": [ "Farm_Forest", "Fish" ],
			"Fields": { 
				"(O)159": {"Chance": 0.13},
				"(O)160": {"Chance": 0.14},
				"(O)163": {"Chance": 0.07},
				"(O)682": {"Chance": 0.07},
				"(O)775": {"Chance": 0.10},
					  },
			    "When": {"Legendary Fish On Farm": true, "Legendary Fish Spawn Rates": "Rare (7-14%)"},
	    },
		{
			"LogName": "Legendary Fish Spawn Rates Farm Forest Very Rare",
			"Action": "EditData",
			"Target": "Data/Locations",
			"TargetField": [ "Farm_Forest", "Fish" ],
			"Fields": { 
				"(O)159": {"Chance": 0.05},
				"(O)160": {"Chance": 0.05},
				"(O)163": {"Chance": 0.05},
				"(O)682": {"Chance": 0.05},
				"(O)775": {"Chance": 0.05},
					  },
			    "When": {"Legendary Fish On Farm": true, "Legendary Fish Spawn Rates": "Very Rare (5%)"},
	    },
		{
			"LogName": "Legendary Fish Spawn Rates Farm Forest Near Impossible",
			"Action": "EditData",
			"Target": "Data/Locations",
			"TargetField": [ "Farm_Forest", "Fish" ],
			"Fields": { 
				"(O)159": {"Chance": 0.01},
				"(O)160": {"Chance": 0.01},
				"(O)163": {"Chance": 0.01},
				"(O)682": {"Chance": 0.01},
				"(O)775": {"Chance": 0.01},
					  },
			    "When": {"Legendary Fish On Farm": true, "Legendary Fish Spawn Rates": "Near Impossible (1%)"},
	    },
		{
			"LogName": "Legendary Fish Spawn Rates Farm FourCorners Common",
			"Action": "EditData",
			"Target": "Data/Locations",
			"TargetField": [ "Farm_FourCorners", "Fish" ],
			"Fields": { 
				"(O)159": {"Chance": 0.2},
				"(O)160": {"Chance": 0.2},
				"(O)163": {"Chance": 0.2},
				"(O)682": {"Chance": 0.2},
				"(O)775": {"Chance": 0.2},
					  },
			    "When": {"Legendary Fish On Farm": true, "Legendary Fish Spawn Rates": "Common (20%)"},
	    },
		{
			"LogName": "Legendary Fish Spawn Rates Farm FourCorners More Common",
			"Action": "EditData",
			"Target": "Data/Locations",
			"TargetField": [ "Farm_FourCorners", "Fish" ],
			"Fields": { 
				"(O)159": {"Chance": 0.3},
				"(O)160": {"Chance": 0.3},
				"(O)163": {"Chance": 0.3},
				"(O)682": {"Chance": 0.3},
				"(O)775": {"Chance": 0.3},
					  },
			    "When": {"Legendary Fish On Farm": true, "Legendary Fish Spawn Rates": "More Common (30%)"},
	    },
		{
			"LogName": "Legendary Fish Spawn Rates Farm FourCorners Very Common",
			"Action": "EditData",
			"Target": "Data/Locations",
			"TargetField": [ "Farm_FourCorners", "Fish" ],
			"Fields": { 
				"(O)159": {"Chance": 0.5},
				"(O)160": {"Chance": 0.5},
				"(O)163": {"Chance": 0.5},
				"(O)682": {"Chance": 0.5},
				"(O)775": {"Chance": 0.5},
					  },
			    "When": {"Legendary Fish On Farm": true, "Legendary Fish Spawn Rates": "Very Common (50%)"},
	    },
		{
			"LogName": "Legendary Fish Spawn Rates Farm FourCorners Rare",
			"Action": "EditData",
			"Target": "Data/Locations",
			"TargetField": [ "Farm_FourCorners", "Fish" ],
			"Fields": { 
				"(O)159": {"Chance": 0.13},
				"(O)160": {"Chance": 0.14},
				"(O)163": {"Chance": 0.07},
				"(O)682": {"Chance": 0.07},
				"(O)775": {"Chance": 0.10},
					  },
			    "When": {"Legendary Fish On Farm": true, "Legendary Fish Spawn Rates": "Rare (7-14%)"},
	    },
		{
			"LogName": "Legendary Fish Spawn Rates Farm FourCorners Very Rare",
			"Action": "EditData",
			"Target": "Data/Locations",
			"TargetField": [ "Farm_FourCorners", "Fish" ],
			"Fields": { 
				"(O)159": {"Chance": 0.05},
				"(O)160": {"Chance": 0.05},
				"(O)163": {"Chance": 0.05},
				"(O)682": {"Chance": 0.05},
				"(O)775": {"Chance": 0.05},
					  },
			    "When": {"Legendary Fish On Farm": true, "Legendary Fish Spawn Rates": "Very Rare (5%)"},
	    },
		{
			"LogName": "Legendary Fish Spawn Rates Farm FourCorners Near Impossible",
			"Action": "EditData",
			"Target": "Data/Locations",
			"TargetField": [ "Farm_FourCorners", "Fish" ],
			"Fields": { 
				"(O)159": {"Chance": 0.01},
				"(O)160": {"Chance": 0.01},
				"(O)163": {"Chance": 0.01},
				"(O)682": {"Chance": 0.01},
				"(O)775": {"Chance": 0.01},
					  },
			    "When": {"Legendary Fish On Farm": true, "Legendary Fish Spawn Rates": "Near Impossible (1%)"},
	    },
		{
			"LogName": "Legendary Fish Spawn Rates Farm Hilltop Common",
			"Action": "EditData",
			"Target": "Data/Locations",
			"TargetField": [ "Farm_Hilltop", "Fish" ],
			"Fields": { 
				"(O)159": {"Chance": 0.2},
				"(O)160": {"Chance": 0.2},
				"(O)163": {"Chance": 0.2},
				"(O)682": {"Chance": 0.2},
				"(O)775": {"Chance": 0.2},
					  },
			    "When": {"Legendary Fish On Farm": true, "Legendary Fish Spawn Rates": "Common (20%)"},
	    },
		{
			"LogName": "Legendary Fish Spawn Rates Farm Hilltop More Common",
			"Action": "EditData",
			"Target": "Data/Locations",
			"TargetField": [ "Farm_Hilltop", "Fish" ],
			"Fields": { 
				"(O)159": {"Chance": 0.3},
				"(O)160": {"Chance": 0.3},
				"(O)163": {"Chance": 0.3},
				"(O)682": {"Chance": 0.3},
				"(O)775": {"Chance": 0.3},
					  },
			    "When": {"Legendary Fish On Farm": true, "Legendary Fish Spawn Rates": "More Common (30%)"},
	    },
		{
			"LogName": "Legendary Fish Spawn Rates Farm Hilltop Very Common",
			"Action": "EditData",
			"Target": "Data/Locations",
			"TargetField": [ "Farm_Hilltop", "Fish" ],
			"Fields": { 
				"(O)159": {"Chance": 0.5},
				"(O)160": {"Chance": 0.5},
				"(O)163": {"Chance": 0.5},
				"(O)682": {"Chance": 0.5},
				"(O)775": {"Chance": 0.5},
					  },
			    "When": {"Legendary Fish On Farm": true, "Legendary Fish Spawn Rates": "Very Common (50%)"},
	    },
		{
			"LogName": "Legendary Fish Spawn Rates Farm Hilltop Rare",
			"Action": "EditData",
			"Target": "Data/Locations",
			"TargetField": [ "Farm_Hilltop", "Fish" ],
			"Fields": { 
				"(O)159": {"Chance": 0.13},
				"(O)160": {"Chance": 0.14},
				"(O)163": {"Chance": 0.07},
				"(O)682": {"Chance": 0.07},
				"(O)775": {"Chance": 0.10},
					  },
			    "When": {"Legendary Fish On Farm": true, "Legendary Fish Spawn Rates": "Rare (7-14%)"},
	    },
		{
			"LogName": "Legendary Fish Spawn Rates Farm Hilltop Very Rare",
			"Action": "EditData",
			"Target": "Data/Locations",
			"TargetField": [ "Farm_Hilltop", "Fish" ],
			"Fields": { 
				"(O)159": {"Chance": 0.05},
				"(O)160": {"Chance": 0.05},
				"(O)163": {"Chance": 0.05},
				"(O)682": {"Chance": 0.05},
				"(O)775": {"Chance": 0.05},
					  },
			    "When": {"Legendary Fish On Farm": true, "Legendary Fish Spawn Rates": "Very Rare (5%)"},
	    },
		{
			"LogName": "Legendary Fish Spawn Rates Farm Hilltop Near Impossible",
			"Action": "EditData",
			"Target": "Data/Locations",
			"TargetField": [ "Farm_Hilltop", "Fish" ],
			"Fields": { 
				"(O)159": {"Chance": 0.01},
				"(O)160": {"Chance": 0.01},
				"(O)163": {"Chance": 0.01},
				"(O)682": {"Chance": 0.01},
				"(O)775": {"Chance": 0.01},
					  },
			    "When": {"Legendary Fish On Farm": true, "Legendary Fish Spawn Rates": "Near Impossible (1%)"},
	    },
		{
			"LogName": "Legendary Fish Spawn Rates Farm Riverland Common",
			"Action": "EditData",
			"Target": "Data/Locations",
			"TargetField": [ "Farm_Riverland", "Fish" ],
			"Fields": { 
				"(O)159": {"Chance": 0.2},
				"(O)160": {"Chance": 0.2},
				"(O)163": {"Chance": 0.2},
				"(O)682": {"Chance": 0.2},
				"(O)775": {"Chance": 0.2},
					  },
			    "When": {"Legendary Fish On Farm": true, "Legendary Fish Spawn Rates": "Common (20%)"},
	    },
		{
			"LogName": "Legendary Fish Spawn Rates Farm Riverland More Common",
			"Action": "EditData",
			"Target": "Data/Locations",
			"TargetField": [ "Farm_Riverland", "Fish" ],
			"Fields": { 
				"(O)159": {"Chance": 0.3},
				"(O)160": {"Chance": 0.3},
				"(O)163": {"Chance": 0.3},
				"(O)682": {"Chance": 0.3},
				"(O)775": {"Chance": 0.3},
					  },
			    "When": {"Legendary Fish On Farm": true, "Legendary Fish Spawn Rates": "More Common (30%)"},
	    },
		{
			"LogName": "Legendary Fish Spawn Rates Farm Riverland Very Common",
			"Action": "EditData",
			"Target": "Data/Locations",
			"TargetField": [ "Farm_Riverland", "Fish" ],
			"Fields": { 
				"(O)159": {"Chance": 0.5},
				"(O)160": {"Chance": 0.5},
				"(O)163": {"Chance": 0.5},
				"(O)682": {"Chance": 0.5},
				"(O)775": {"Chance": 0.5},
					  },
			    "When": {"Legendary Fish On Farm": true, "Legendary Fish Spawn Rates": "Very Common (50%)"},
	    },
		{
			"LogName": "Legendary Fish Spawn Rates Farm Riverland Rare",
			"Action": "EditData",
			"Target": "Data/Locations",
			"TargetField": [ "Farm_Riverland", "Fish" ],
			"Fields": { 
				"(O)159": {"Chance": 0.13},
				"(O)160": {"Chance": 0.14},
				"(O)163": {"Chance": 0.07},
				"(O)682": {"Chance": 0.07},
				"(O)775": {"Chance": 0.10},
					  },
			    "When": {"Legendary Fish On Farm": true, "Legendary Fish Spawn Rates": "Rare (7-14%)"},
	    },
		{
			"LogName": "Legendary Fish Spawn Rates Farm Riverland Very Rare",
			"Action": "EditData",
			"Target": "Data/Locations",
			"TargetField": [ "Farm_Riverland", "Fish" ],
			"Fields": { 
				"(O)159": {"Chance": 0.05},
				"(O)160": {"Chance": 0.05},
				"(O)163": {"Chance": 0.05},
				"(O)682": {"Chance": 0.05},
				"(O)775": {"Chance": 0.05},
					  },
			    "When": {"Legendary Fish On Farm": true, "Legendary Fish Spawn Rates": "Very Rare (5%)"},
	    },
		{
			"LogName": "Legendary Fish Spawn Rates Farm Riverland Near Impossible",
			"Action": "EditData",
			"Target": "Data/Locations",
			"TargetField": [ "Farm_Riverland", "Fish" ],
			"Fields": { 
				"(O)159": {"Chance": 0.01},
				"(O)160": {"Chance": 0.01},
				"(O)163": {"Chance": 0.01},
				"(O)682": {"Chance": 0.01},
				"(O)775": {"Chance": 0.01},
					  },
			    "When": {"Legendary Fish On Farm": true, "Legendary Fish Spawn Rates": "Near Impossible (1%)"},
	    },
		{
			"LogName": "Legendary Fish Spawn Rates Farm Wilderness Common",
			"Action": "EditData",
			"Target": "Data/Locations",
			"TargetField": [ "Farm_Wilderness", "Fish" ],
			"Fields": { 
				"(O)159": {"Chance": 0.2},
				"(O)160": {"Chance": 0.2},
				"(O)163": {"Chance": 0.2},
				"(O)682": {"Chance": 0.2},
				"(O)775": {"Chance": 0.2},
					  },
			    "When": {"Legendary Fish On Farm": true, "Legendary Fish Spawn Rates": "Common (20%)"},
	    },
		{
			"LogName": "Legendary Fish Spawn Rates Farm Wilderness More Common",
			"Action": "EditData",
			"Target": "Data/Locations",
			"TargetField": [ "Farm_Wilderness", "Fish" ],
			"Fields": { 
				"(O)159": {"Chance": 0.3},
				"(O)160": {"Chance": 0.3},
				"(O)163": {"Chance": 0.3},
				"(O)682": {"Chance": 0.3},
				"(O)775": {"Chance": 0.3},
					  },
			    "When": {"Legendary Fish On Farm": true, "Legendary Fish Spawn Rates": "More Common (30%)"},
	    },
		{
			"LogName": "Legendary Fish Spawn Rates Farm Wilderness Very Common",
			"Action": "EditData",
			"Target": "Data/Locations",
			"TargetField": [ "Farm_Wilderness", "Fish" ],
			"Fields": { 
				"(O)159": {"Chance": 0.5},
				"(O)160": {"Chance": 0.5},
				"(O)163": {"Chance": 0.5},
				"(O)682": {"Chance": 0.5},
				"(O)775": {"Chance": 0.5},
					  },
			    "When": {"Legendary Fish On Farm": true, "Legendary Fish Spawn Rates": "Very Common (50%)"},
	    },
		{
			"LogName": "Legendary Fish Spawn Rates Farm Wilderness Rare",
			"Action": "EditData",
			"Target": "Data/Locations",
			"TargetField": [ "Farm_Wilderness", "Fish" ],
			"Fields": { 
				"(O)159": {"Chance": 0.13},
				"(O)160": {"Chance": 0.14},
				"(O)163": {"Chance": 0.07},
				"(O)682": {"Chance": 0.07},
				"(O)775": {"Chance": 0.10},
					  },
			    "When": {"Legendary Fish On Farm": true, "Legendary Fish Spawn Rates": "Rare (7-14%)"},
	    },
		{
			"LogName": "Legendary Fish Spawn Rates Farm Wilderness Very Rare",
			"Action": "EditData",
			"Target": "Data/Locations",
			"TargetField": [ "Farm_Wilderness", "Fish" ],
			"Fields": { 
				"(O)159": {"Chance": 0.05},
				"(O)160": {"Chance": 0.05},
				"(O)163": {"Chance": 0.05},
				"(O)682": {"Chance": 0.05},
				"(O)775": {"Chance": 0.05},
					  },
			    "When": {"Legendary Fish On Farm": true, "Legendary Fish Spawn Rates": "Very Rare (5%)"},
	    },
		{
			"LogName": "Legendary Fish Spawn Rates Farm Wilderness Near Impossible",
			"Action": "EditData",
			"Target": "Data/Locations",
			"TargetField": [ "Farm_Wilderness", "Fish" ],
			"Fields": { 
				"(O)159": {"Chance": 0.01},
				"(O)160": {"Chance": 0.01},
				"(O)163": {"Chance": 0.01},
				"(O)682": {"Chance": 0.01},
				"(O)775": {"Chance": 0.01},
					  },
			    "When": {"Legendary Fish On Farm": true, "Legendary Fish Spawn Rates": "Near Impossible (1%)"},
	    },
		{
			"LogName": "Legendary Fish Spawn Rates Farm Meadowlands Common",
			"Action": "EditData",
			"Target": "Data/Locations",
			"TargetField": [ "Farm_MeadowlandsFarm", "Fish" ],
			"Fields": { 
				"(O)159": {"Chance": 0.2},
				"(O)160": {"Chance": 0.2},
				"(O)163": {"Chance": 0.2},
				"(O)682": {"Chance": 0.2},
				"(O)775": {"Chance": 0.2},
					  },
			    "When": {"Legendary Fish On Farm": true, "Legendary Fish Spawn Rates": "Common (20%)"},
	    },
		{
			"LogName": "Legendary Fish Spawn Rates Farm Meadowlands More Common",
			"Action": "EditData",
			"Target": "Data/Locations",
			"TargetField": [ "Farm_MeadowlandsFarm", "Fish" ],
			"Fields": { 
				"(O)159": {"Chance": 0.3},
				"(O)160": {"Chance": 0.3},
				"(O)163": {"Chance": 0.3},
				"(O)682": {"Chance": 0.3},
				"(O)775": {"Chance": 0.3},
					  },
			    "When": {"Legendary Fish On Farm": true, "Legendary Fish Spawn Rates": "More Common (30%)"},
	    },
		{
			"LogName": "Legendary Fish Spawn Rates Farm Meadowlands Very Common",
			"Action": "EditData",
			"Target": "Data/Locations",
			"TargetField": [ "Farm_MeadowlandsFarm", "Fish" ],
			"Fields": { 
				"(O)159": {"Chance": 0.5},
				"(O)160": {"Chance": 0.5},
				"(O)163": {"Chance": 0.5},
				"(O)682": {"Chance": 0.5},
				"(O)775": {"Chance": 0.5},
					  },
			    "When": {"Legendary Fish On Farm": true, "Legendary Fish Spawn Rates": "Very Common (50%)"},
	    },
		{
			"LogName": "Legendary Fish Spawn Rates Farm Meadowlands Rare",
			"Action": "EditData",
			"Target": "Data/Locations",
			"TargetField": [ "Farm_MeadowlandsFarm", "Fish" ],
			"Fields": { 
				"(O)159": {"Chance": 0.13},
				"(O)160": {"Chance": 0.14},
				"(O)163": {"Chance": 0.07},
				"(O)682": {"Chance": 0.07},
				"(O)775": {"Chance": 0.10},
					  },
			    "When": {"Legendary Fish On Farm": true, "Legendary Fish Spawn Rates": "Rare (7-14%)"},
	    },
		{
			"LogName": "Legendary Fish Spawn Rates Farm Meadowlands Very Rare",
			"Action": "EditData",
			"Target": "Data/Locations",
			"TargetField": [ "Farm_MeadowlandsFarm", "Fish" ],
			"Fields": { 
				"(O)159": {"Chance": 0.05},
				"(O)160": {"Chance": 0.05},
				"(O)163": {"Chance": 0.05},
				"(O)682": {"Chance": 0.05},
				"(O)775": {"Chance": 0.05},
					  },
			    "When": {"Legendary Fish On Farm": true, "Legendary Fish Spawn Rates": "Very Rare (5%)"},
	    },
		{
			"LogName": "Legendary Fish Spawn Rates Farm Meadowlands Near Impossible",
			"Action": "EditData",
			"Target": "Data/Locations",
			"TargetField": [ "Farm_MeadowlandsFarm", "Fish" ],
			"Fields": { 
				"(O)159": {"Chance": 0.01},
				"(O)160": {"Chance": 0.01},
				"(O)163": {"Chance": 0.01},
				"(O)682": {"Chance": 0.01},
				"(O)775": {"Chance": 0.01},
					  },
			    "When": {"Legendary Fish On Farm": true, "Legendary Fish Spawn Rates": "Near Impossible (1%)"},
	    },
	]
}